analysis/lcms/scaling_factor.py
analysis/lcms/IBD/ibd_pMS2_mol_network.py
analysis/lcms/IBD/ihmp2_analysis.py
analysis/lcms/IBD/ihmp2_heatmap.py
analysis/lcms/IBD/ihmp2_match_to_identified_list.py
analysis/lcms/IBD/ihmp2_stats_analysis.py
analysis/lcms/IBD/ihmp2_tSNE.py
analysis/lcms/IBD/data/ibd_demo_ms2_fig.py
analysis/lcms/IBD/old/_ihmp2_upset_plot.py
analysis/lcms/IBD/old/_workbench_api.py
analysis/lcms/IBD/old/ihmp2_analysis.py
analysis/lcms/IBD/old/ihmp2_heatmap.py
analysis/lcms/IBD/old/ihmp2_match_to_identified_list.py
analysis/lcms/IBD/old/ihmp2_stats_analysis.py
analysis/lcms/IBD/old/ihmp2_umap.py
analysis/lcms/all_datasets/all_datasets_analysis.py
analysis/lcms/all_datasets/bar_plot.py
analysis/lcms/all_datasets/plot_heatmap.py
analysis/lcms/ms1_masst_demo/masst_demo_ms2_fig.py
analysis/lcms/ms1_masst_demo/ms1_masst.py
analysis/lcms/nist/nist_analysis.py
analysis/lcms/nist/nist_barplot.py
analysis/lcms/nist/nist_boxplot_peakHeight.py
analysis/lcms/nist/nist_boxplot_vertical.py
analysis/lcms/nist/nist_cmpd_class_scatter.py
analysis/lcms/nist/nist_demo_ms2_fig.py
analysis/lcms/nist/nist_mol_network.py
analysis/lcms/nist/nist_phe_C3_scatter_plot.py
analysis/lcms/nist/nist_spec_sim.py
analysis/lcms/nist/nist_structure_similarity.py
analysis/lcms/nist/revcos_main.py
analysis/lcms/nist/old/nist_analysis.py
analysis/lcms/nist/old/nist_annotation_bar.py
analysis/lcms/nist/old/nist_annotation_venn.py
analysis/lcms/nist/old/nist_demo_ms2_fig.py
analysis/lcms/nist/old/nist_demo_ms2_multi_adduct.py
analysis/lcms/nist/old/nist_demo_xics.py
analysis/lcms/nist/old/nist_feature_intensity_distribution.py
analysis/lcms/nist/old/nist_plot_ce.py
analysis/lcms/plot_all_mirror/all_ms2plot_lcms.py
analysis/lcms/std/_preprocess_ms2.py
analysis/lcms/std/choose_scale_k.py
analysis/lcms/std/flash_cos.py
analysis/lcms/std/make_library.py
analysis/lcms/std/std_ms2_fig.py
analysis/lcms/std/std_score_distribution.py
analysis/msi/cell/cell_analysis.py
ms1_id-0.2.1.dist-info/LICENSE
ms1_id-0.2.1.dist-info/METADATA
ms1_id-0.2.1.dist-info/WHEEL
ms1_id-0.2.1.dist-info/entry_points.txt
ms1_id-0.2.1.dist-info/top_level.txt
ms1_id-0.2.1.dist-info/RECORD
