Metadata-Version: 2.1
Name: ms1_id
Version: 0.2.1
Summary: Annotate LC-MS1 data, MS imaging data or pseudo MS/MS spectra using reference MS/MS libraries
Author-email: Shipei Xing <philipxsp@hotmail.com>
License: Apache License
Project-URL: Homepage, https://github.com/Philipbear/ms1_id
Project-URL: Bug Tracker, https://github.com/Philipbear/ms1_id/issues
Classifier: Programming Language :: Python :: 3
Classifier: License :: OSI Approved :: Apache Software License
Classifier: Operating System :: OS Independent
Requires-Python: >=3.9
License-File: LICENSE
Requires-Dist: masscube ==1.0.11
Requires-Dist: numba >=0.56.4
Requires-Dist: pyimzML >=1.5.4
Requires-Dist: requests >=2.28.2
Requires-Dist: pyImagingMSpec >=0.1.4
